smartenough/__init__.py
smartenough/llm.py
smartenough-0.32.dist-info/METADATA
smartenough-0.32.dist-info/WHEEL
smartenough-0.32.dist-info/licenses/LICENSE
smartenough-0.32.dist-info/RECORD
