Metadata-Version: 2.3
Name: smartenough
Version: 0.32
Summary: Convert cheap LLMs into efficient, validated API calls.
Project-URL: Homepage, https://codeberg.org/Medusa-Intelligence-Corp/smartenough
Project-URL: Issues, https://codeberg.org/Medusa-Intelligence-Corp/smartenough/issues
Author-email: Medusa Intelligence Corporation <info@medusaintel.co>
License-File: LICENSE
Classifier: License :: OSI Approved :: GNU General Public License v3 or later (GPLv3+)
Classifier: Operating System :: OS Independent
Classifier: Programming Language :: Python :: 3
Requires-Python: >=3.7
Requires-Dist: anthropic>=0.31.2
Requires-Dist: beautifulsoup4>=4.12.3
Requires-Dist: google-generativeai>=0.7.2
Requires-Dist: mistralai>=1.0.1
Requires-Dist: openai>=1.36.0
Requires-Dist: requests>=2.32.3
Requires-Dist: urlextract>=1.9.0
Requires-Dist: validators>=0.33.0
